CHANGES.txt
MANIFEST.in
fakery.py
requirements.txt
setup.py
fakery.egg-info/PKG-INFO
fakery.egg-info/SOURCES.txt
fakery.egg-info/dependency_links.txt
fakery.egg-info/requires.txt
fakery.egg-info/top_level.txt