Metadata-Version: 1.0
Name: fakery
Version: 0.1.2
Summary: Trying to make fudge mocks in Python easier.
Home-page: UNKNOWN
Author: Gary Johnson
Author-email: gary@gjtt.com
License: MIT License
Platform: UNKNOWN
